setup.py
ramziiss_distributions/Binomialdistribution.py
ramziiss_distributions/Gaussiandistribution.py
ramziiss_distributions/Generaldistribution.py
ramziiss_distributions/__init__.py
ramziiss_distributions.egg-info/PKG-INFO
ramziiss_distributions.egg-info/SOURCES.txt
ramziiss_distributions.egg-info/dependency_links.txt
ramziiss_distributions.egg-info/not-zip-safe
ramziiss_distributions.egg-info/top_level.txt