Metadata-Version: 1.0
Name: ramziiss-distributions
Version: 0.1
Summary: Gaussian and binomial distributions
Home-page: UNKNOWN
Author: ramziiss
Author-email: ramziiss@gmail.com
License: UNKNOWN
Platform: UNKNOWN
